endstone/__init__.py
endstone/_internal/__init__.py
endstone/_internal/bootstrap/__init__.py
endstone/_internal/bootstrap/base.py
endstone/_internal/bootstrap/linux.py
endstone/_internal/bootstrap/windows.py
endstone/_internal/endstone_python.cp311-win_amd64.pyd
endstone/_internal/endstone_python.pyi
endstone/_internal/endstone_runtime.dll
endstone/_internal/endstone_runtime.lib
endstone/_internal/plugin_loader.py
endstone/_internal/version.py
endstone/command.py
endstone/logger.py
endstone/plugin.py
endstone/server.py
endstone/util.py
endstone-1.20.71.0.dist-info/METADATA
endstone-1.20.71.0.dist-info/WHEEL
endstone-1.20.71.0.dist-info/entry_points.txt
endstone-1.20.71.0.dist-info/licenses/LICENSE
endstone-1.20.71.0.dist-info/RECORD
