Metadata-Version: 2.1
Name: endstone
Version: 1.20.71.0
Summary: Endstone offers a plugin API for Bedrock Dedicated Servers, supporting both Python and C++.
Keywords: plugin python minecraft bedrock
Author-Email: Vincent Wu <magicdroidx@gmail.com>
License:                                  Apache License
Classifier: Programming Language :: Python
Classifier: Programming Language :: Python :: 3
Classifier: Programming Language :: Python :: 3.9
Classifier: Programming Language :: Python :: 3.10
Classifier: Programming Language :: Python :: 3.11
Classifier: Programming Language :: Python :: 3.12
Classifier: License :: OSI Approved :: Apache Software License
Classifier: Operating System :: Microsoft :: Windows
Classifier: Operating System :: POSIX :: Linux
Project-URL: Discussions, https://github.com/orgs/EndstoneMC/discussions
Project-URL: Documentation, https://endstone.readthedocs.io
Project-URL: Homepage, https://github.com/EndstoneMC/endstone
Project-URL: Issues, https://github.com/EndstoneMC/endstone/issues
Requires-Python: >=3.9
Requires-Dist: click
Requires-Dist: requests
Requires-Dist: rich
Requires-Dist: tomli; python_version < "3.11"
Requires-Dist: packaging
Requires-Dist: pytest; extra == "test"
Provides-Extra: test
License-File: LICENSE
